wplzx/__init__.py
wplzx/core.py
wplzx/wzcc/__init__.py
wplzx/wzcc/quantize.py
wplzx/wzcc/verify.py
wplzx-0.0.3.dist-info/licenses/LICENSE
wplzx-0.0.3.dist-info/METADATA
wplzx-0.0.3.dist-info/WHEEL
wplzx-0.0.3.dist-info/top_level.txt
wplzx-0.0.3.dist-info/RECORD
